{
  "availability": {
    "pickupAtLocationAvailability": [
      {
      "availabilityType" : "IN_STOCK",
      "fulfillmentTime" : {
          "unit" : "DAY",
          "value" : "1"
        },
        "merchantLocationKey": "string",
        "quantity": "12"
      }
    ],
    "shipToLocationAvailability": {
      "quantity": "14"
    }
  },
  "condition": "USED_GOOD",
  "conditionDescription": "string",
  "packageWeightAndSize": {
    "dimensions": {
      "height": "12",
      "length": "12",
      "unit": "INCH",
      "width": "12"
    },
    "packageType": "LETTER",
    "weight": {
      "unit": "OUNCE",
      "value": "12"
    }
  },
  "product": {
    "brand": "string",
    "description": "string",
    "mpn": "string",
    "subtitle": "string",
    "title": "string"
  }
}